<fest:template xmlns:fest="http://fest.mail.ru" context_name="json">

    <div class="window">
        <a href="#" class="window__a_decoration-none" >
            <span class="window__span_hover-blue window__span_green"> Connect FOUR </span>
        </a>
        <a href="#game" class="window__a_decoration-none">
            <span class="window__span_hover-blue window__span_orange">Start</span>
        </a>
        <a href="#scoreboard" class="window__a_decoration-none">
            <span class="window__span_hover-blue window__span_orange">Score</span>
        </a>
		<a href="#login" class="window__a_decoration-none">
    		<span class="window__span_hover-blue window__span_orange">Login</span>
    	</a>
		<a href="#signup" class="window__a_decoration-none">
    		<span class="window__span_orange window__span_hover-blue window__span_text-size-little">Register now!</span>
    	</a>
    </div>
</fest:template>

